Metadata-Version: 2.1
Name: LLM-Souverain
Version: 0.0.6
Summary: LLM addons for Orange Data Mining !
Home-page: 
Author: 
Author-email: 
Keywords: orange3 add-on
License-File: License.txt
Requires-Dist: gpt4all==2.2.1
Requires-Dist: Orange3-Textable==3.1.11
